gensysco/__init__.py
gensysco/__main__.py
gensysco/absweb/__init__.py
gensysco/coredb/__init__.py
gensysco-1.2.4.dist-info/LICENSE.txt
gensysco-1.2.4.dist-info/METADATA
gensysco-1.2.4.dist-info/WHEEL
gensysco-1.2.4.dist-info/top_level.txt
gensysco-1.2.4.dist-info/RECORD
