Metadata-Version: 2.1
Name: gensysco
Version: 1.2.4
Summary: gensysco
Home-page: https://github.com/pythonsystem/gensysco
Author: Digital Community
License: MIT
License-File: LICENSE.txt
Requires-Dist: httpx ==0.27.0
Requires-Dist: prisma ==0.9.1
